kongcore/__init__.py
Rkongcore-0.0.1.dist-info/LICENSE
Rkongcore-0.0.1.dist-info/METADATA
Rkongcore-0.0.1.dist-info/WHEEL
Rkongcore-0.0.1.dist-info/top_level.txt
Rkongcore-0.0.1.dist-info/RECORD
